{
  "updatedAt": "2026-06-09T09:43:54.239Z",
  "posts": [
    {
      "slug": "mediheal-toner-pad-200-stock-a000000255385",
      "title": "메디힐 더마 토너패드 200매 후기처럼 보기｜민트 네모패드 올리브영 재고",
      "description": "메디힐 더마 토너패드 200매의 민트 용기 색감, 네모패드 크기, 촉촉한 사진 느낌을 자연스럽게 보고 올리브영 재고와 구매 링크까지 바로 이어볼 수 있게 정리했습니다.",
      "rawName": "[6월 올영픽/한정기획] 메디힐 더마 토너패드 200매 대용량 7종 기획 골라담기 (+휴대용 케이스)",
      "cleanName": "메디힐 더마 토너패드 200매 대용량 7종 기획 골라담기 (+휴대용 케이스)",
      "shortName": "메디힐 더마 토너패드 200매",
      "brand": "메디힐",
      "categoryName": "토너패드·마스크팩",
      "badges": [
        "6월 올영픽/한정기획"
      ],
      "goodsNo": "A000000255385",
      "rank": 1,
      "viewCount": 2376,
      "itemId": "8800364101267",
      "categoryId": "10000010009",
      "publishedAt": "2026-06-09T09:43:50.283+00:00",
      "modifiedAt": "2026-06-09T09:43:50.283+00:00",
      "rankingDate": "2026-06-09",
      "rankingDateText": "2026.06.09.18:43",
      "query": "메디힐 더마 토너패드 200매",
      "image": "/images/blog/mediheal-toner-pad-200-stock-a000000255385.png",
      "url": "/blog/mediheal-toner-pad-200-stock-a000000255385/",
      "source": "oliveyoung-view-ranking"
    },
    {
      "slug": "mediheal-sun-serum-stock-a000000255391",
      "title": "메디힐 마데카소사이드 수분 선세럼 50g 후기처럼 보기｜수분 선세럼 올리브영 재고",
      "description": "메디힐 마데카소사이드 수분 선세럼 50g의 흰 튜브, 민트 포인트, 촉촉한 선케어 사진 느낌을 자연스럽게 보고 올리브영 재고와 구매 링크까지 바로 이어볼 수 있게 정리했습니다.",
      "rawName": "[6월 올영픽/한정기획] 메디힐 마데카소사이드 수분 선세럼 흔적 리페어 50+50g",
      "cleanName": "메디힐 마데카소사이드 수분 선세럼 흔적 리페어 50+50g",
      "shortName": "메디힐 마데카소사이드 수분 선세럼 50g",
      "brand": "메디힐",
      "categoryName": "선케어",
      "badges": [
        "6월 올영픽/한정기획"
      ],
      "goodsNo": "A000000255391",
      "rank": 2,
      "viewCount": 1059,
      "itemId": "8800364101595",
      "categoryId": "10000010011",
      "publishedAt": "2026-06-09T09:43:50.283+00:00",
      "modifiedAt": "2026-06-09T09:43:50.283+00:00",
      "rankingDate": "2026-06-09",
      "rankingDateText": "2026.06.09.18:43",
      "query": "메디힐 마데카소사이드 수분 선세럼 50g",
      "image": "/images/blog/mediheal-sun-serum-stock-a000000255391.png",
      "url": "/blog/mediheal-sun-serum-stock-a000000255391/",
      "source": "oliveyoung-view-ranking"
    },
    {
      "slug": "mediheal-gel-mask-stock-a000000239102",
      "title": "메디힐 하이퍼 겔마스크 후기처럼 보기｜하이퍼 겔마스크 올리브영 재고",
      "description": "메디힐 하이퍼 겔마스크의 핑크·보라·하늘색 박스, 촉촉한 겔마스크 사진 느낌을 자연스럽게 보고 올리브영 재고와 구매 링크까지 바로 이어볼 수 있게 정리했습니다.",
      "rawName": "[단독기획 8+1매] 메디힐 하이퍼 겔마스크 4종 (콜라겐/PDRN/마데카소사이드/히알루론산)",
      "cleanName": "메디힐 하이퍼 겔마스크 4종 (콜라겐/PDRN/마데카소사이드/히알루론산)",
      "shortName": "메디힐 하이퍼 겔마스크",
      "brand": "메디힐",
      "categoryName": "토너패드·마스크팩",
      "badges": [
        "단독기획 8+1매"
      ],
      "goodsNo": "A000000239102",
      "rank": 3,
      "viewCount": 862,
      "itemId": "8809936747735",
      "categoryId": "10000010009",
      "publishedAt": "2026-06-09T09:43:50.283+00:00",
      "modifiedAt": "2026-06-09T09:43:50.283+00:00",
      "rankingDate": "2026-06-09",
      "rankingDateText": "2026.06.09.18:43",
      "query": "메디힐 하이퍼 겔마스크",
      "image": "/images/blog/mediheal-gel-mask-stock-a000000239102.png",
      "url": "/blog/mediheal-gel-mask-stock-a000000239102/",
      "source": "oliveyoung-view-ranking"
    },
    {
      "slug": "torriden-serum-stock-a000000256047",
      "title": "토리든 다이브인 저분자 히알루론산 세럼 50ml 후기처럼 보기｜다이브인 세럼 올리브영 재고",
      "description": "토리든 다이브인 저분자 히알루론산 세럼 50ml의 블루 보틀, 스포이드, 촉촉한 수분 세럼 사진 느낌을 자연스럽게 보고 올리브영 재고와 구매 링크까지 바로 이어볼 수 있게 정리했습니다.",
      "rawName": "[NEW/6월올영픽]토리든 다이브인 저분자 히알루론산 세럼 50ml 더블 기획 (밸풀 세럼 20ml+선크림 20ml)",
      "cleanName": "토리든 다이브인 저분자 히알루론산 세럼 50ml 더블 기획 (밸풀 세럼 20ml+선크림 20ml)",
      "shortName": "토리든 다이브인 저분자 히알루론산 세럼 50ml",
      "brand": "토리든",
      "categoryName": "스킨케어",
      "badges": [
        "NEW/6월올영픽"
      ],
      "goodsNo": "A000000256047",
      "rank": 1,
      "viewCount": 2759,
      "itemId": "8809784607779",
      "categoryId": "10000010001",
      "publishedAt": "2026-06-09T08:46:24.819+00:00",
      "modifiedAt": "2026-06-09T08:46:24.819+00:00",
      "rankingDate": "2026-06-09",
      "rankingDateText": "2026.06.09.17:46",
      "query": "토리든 다이브인 저분자 히알루론산 세럼 50ml",
      "image": "/images/blog/torriden-serum-stock-a000000256047.png",
      "url": "/blog/torriden-serum-stock-a000000256047/",
      "source": "oliveyoung-view-ranking"
    }
  ]
}
